ansible_targetnode_setup/__init__.py
ansible_targetnode_setup/controller.py
ansible_targetnode_setup-0.1.dist-info/LICENSE
ansible_targetnode_setup-0.1.dist-info/METADATA
ansible_targetnode_setup-0.1.dist-info/WHEEL
ansible_targetnode_setup-0.1.dist-info/entry_points.txt
ansible_targetnode_setup-0.1.dist-info/top_level.txt
ansible_targetnode_setup-0.1.dist-info/RECORD
